LICENSE
README.md
pyproject.toml
setup.py
QuickReaderPDF/__init__.py
QuickReaderPDF/__main__.py
QuickReaderPDF/pdfeditor.py
QuickReaderPDF.egg-info/PKG-INFO
QuickReaderPDF.egg-info/SOURCES.txt
QuickReaderPDF.egg-info/dependency_links.txt
QuickReaderPDF.egg-info/requires.txt
QuickReaderPDF.egg-info/top_level.txt
QuickReaderPDF/tests/__init__.py
QuickReaderPDF/tests/test_all.py