Metadata-Version: 2.1
Name: QuickReaderPDF
Version: 0.1.3
Summary: This package converts a pdf or a html file that the user wants to read to an new pdf file, which can be read faster! The idea is bionic reading, where we bold the first three letters of every word. We hope you enjoy reading your files faster!
Author-email: Shreyas Bhat <shreyasbhat92@gmail.com>
License: MIT License
Project-URL: repository, https://github.com/Sbhat92/QuickReaderPDF
Classifier: Development Status :: 2 - Pre-Alpha
Classifier: Programming Language :: Python :: Implementation :: CPython
Classifier: Programming Language :: Python :: Implementation :: PyPy
Classifier: Programming Language :: Python :: 3
Classifier: Programming Language :: Python :: 3.7
Classifier: Programming Language :: Python :: 3.8
Classifier: Programming Language :: Python :: 3.9
Classifier: Programming Language :: Python :: 3.10
Classifier: Programming Language :: Python :: 3.11
Requires-Python: >=3.7
Provides-Extra: develop
License-File: LICENSE
